awxkit/__init__.py
awxkit/config.py
awxkit/exceptions.py
awxkit/words.py
awxkit/ws.py
awxkit/yaml_file.py
awxkit/api/__init__.py
awxkit/api/client.py
awxkit/api/registry.py
awxkit/api/resources.py
awxkit/api/utils.py
awxkit/api/mixins/__init__.py
awxkit/api/mixins/has_copy.py
awxkit/api/mixins/has_create.py
awxkit/api/mixins/has_instance_groups.py
awxkit/api/mixins/has_notifications.py
awxkit/api/mixins/has_status.py
awxkit/api/mixins/has_survey.py
awxkit/api/mixins/has_variables.py
awxkit/api/pages/__init__.py
awxkit/api/pages/access_list.py
awxkit/api/pages/activity_stream.py
awxkit/api/pages/ad_hoc_commands.py
awxkit/api/pages/api.py
awxkit/api/pages/applications.py
awxkit/api/pages/authtoken.py
awxkit/api/pages/base.py
awxkit/api/pages/bulk.py
awxkit/api/pages/config.py
awxkit/api/pages/credential_input_sources.py
awxkit/api/pages/credentials.py
awxkit/api/pages/dashboard.py
awxkit/api/pages/execution_environments.py
awxkit/api/pages/host_metrics.py
awxkit/api/pages/instance_groups.py
awxkit/api/pages/instances.py
awxkit/api/pages/inventory.py
awxkit/api/pages/job_templates.py
awxkit/api/pages/jobs.py
awxkit/api/pages/labels.py
awxkit/api/pages/mesh_visualizer.py
awxkit/api/pages/metrics.py
awxkit/api/pages/notification_templates.py
awxkit/api/pages/notifications.py
awxkit/api/pages/organizations.py
awxkit/api/pages/page.py
awxkit/api/pages/ping.py
awxkit/api/pages/projects.py
awxkit/api/pages/roles.py
awxkit/api/pages/schedules.py
awxkit/api/pages/settings.py
awxkit/api/pages/subscriptions.py
awxkit/api/pages/survey_spec.py
awxkit/api/pages/system_job_templates.py
awxkit/api/pages/system_jobs.py
awxkit/api/pages/teams.py
awxkit/api/pages/unified_job_templates.py
awxkit/api/pages/unified_jobs.py
awxkit/api/pages/users.py
awxkit/api/pages/workflow_approval_templates.py
awxkit/api/pages/workflow_approvals.py
awxkit/api/pages/workflow_job_nodes.py
awxkit/api/pages/workflow_job_template_nodes.py
awxkit/api/pages/workflow_job_templates.py
awxkit-24.6.1.dist-info/METADATA
awxkit-24.6.1.dist-info/WHEEL
awxkit-24.6.1.dist-info/entry_points.txt
awxkit-24.6.1.dist-info/top_level.txt
awxkit-24.6.1.dist-info/RECORD
